build/lib/build/lib/build/lib/ssak3/__init__.py
build/lib/build/lib/build/lib/ssak3/block.py
build/lib/build/lib/build/lib/ssak3/client.py
build/lib/build/lib/build/lib/ssak3/constants.py
build/lib/build/lib/build/lib/ssak3/errors.py
build/lib/build/lib/build/lib/ssak3/init.py
build/lib/build/lib/build/lib/ssak3/logs.py
build/lib/build/lib/build/lib/ssak3/path.py
build/lib/build/lib/build/lib/ssak3/proxy.py
build/lib/build/lib/build/lib/ssak3/query.py
build/lib/build/lib/build/lib/ssak3/storage.py
build/lib/build/lib/build/lib/ssak3/strategy.py
build/lib/build/lib/build/lib/ssak3/timezone.py
build/lib/build/lib/build/lib/ssak3/utils.py
build/lib/build/lib/ssak3/__init__.py
build/lib/build/lib/ssak3/block.py
build/lib/build/lib/ssak3/client.py
build/lib/build/lib/ssak3/constants.py
build/lib/build/lib/ssak3/errors.py
build/lib/build/lib/ssak3/init.py
build/lib/build/lib/ssak3/logs.py
build/lib/build/lib/ssak3/path.py
build/lib/build/lib/ssak3/proxy.py
build/lib/build/lib/ssak3/query.py
build/lib/build/lib/ssak3/storage.py
build/lib/build/lib/ssak3/strategy.py
build/lib/build/lib/ssak3/timezone.py
build/lib/build/lib/ssak3/utils.py
build/lib/ssak3/__init__.py
build/lib/ssak3/block.py
build/lib/ssak3/client.py
build/lib/ssak3/constants.py
build/lib/ssak3/errors.py
build/lib/ssak3/init.py
build/lib/ssak3/logs.py
build/lib/ssak3/path.py
build/lib/ssak3/proxy.py
build/lib/ssak3/query.py
build/lib/ssak3/storage.py
build/lib/ssak3/strategy.py
build/lib/ssak3/timezone.py
build/lib/ssak3/utils.py
ssak3/__init__.py
ssak3/block.py
ssak3/client.py
ssak3/constants.py
ssak3/errors.py
ssak3/init.py
ssak3/logs.py
ssak3/path.py
ssak3/proxy.py
ssak3/query.py
ssak3/storage.py
ssak3/strategy.py
ssak3/timezone.py
ssak3/utils.py
ssak3/prompts/company_gold_02_01.yaml
ssak3/prompts/company_mart_01_01.yaml
ssak3/prompts/company_mart_01_02.yaml
ssak3/prompts/fruit_color.yaml
ssak3/prompts/name_map.yaml
ssak3/prompts/news_gold_01.yaml
ssak3/prompts/news_gold_02_01.yaml
ssak3-1.1.20.dist-info/LICENSE
ssak3-1.1.20.dist-info/METADATA
ssak3-1.1.20.dist-info/WHEEL
ssak3-1.1.20.dist-info/top_level.txt
ssak3-1.1.20.dist-info/RECORD
