Metadata-Version: 2.1
Name: ssak3
Version: 1.1.20
Summary: ssak3 package
Home-page: https://github.com/bigzzodev
Author: bigzzodev
Author-email: bigzzodev@gmail.com
Classifier: Programming Language :: Python :: 3
Classifier: License :: OSI Approved :: MIT License
Classifier: Operating System :: OS Independent
Requires-Python: >=3.6
License-File: LICENSE
Requires-Dist: apify
Requires-Dist: loguru
Requires-Dist: tzlocal
